illallangi/data/education/__init__.py
illallangi/data/education/__version__.py
illallangi/data/education/apps.py
illallangi/data/education/adapters/__init__.py
illallangi/data/education/adapters/education.py
illallangi/data/education/admin/__init__.py
illallangi/data/education/admin/course.py
illallangi/data/education/checks/__init__.py
illallangi/data/education/checks/education.py
illallangi/data/education/checks/rdf.py
illallangi/data/education/diffsyncmodels/__init__.py
illallangi/data/education/diffsyncmodels/course.py
illallangi/data/education/migrations/0001_initial.py
illallangi/data/education/migrations/__init__.py
illallangi/data/education/models/__init__.py
illallangi/data/education/models/course.py
illallangi/data/education/static/education/courses.jpg
illallangi/data/education/templates/education/course_detail.html
illallangi/data/education/templates/education/course_list.html
illallangi/data/education/views/__init__.py
illallangi/data/education/views/course_detail.py
illallangi/data/education/views/course_list.py
illallangi_data_education-0.3.0.dist-info/METADATA
illallangi_data_education-0.3.0.dist-info/WHEEL
illallangi_data_education-0.3.0.dist-info/entry_points.txt
illallangi_data_education-0.3.0.dist-info/licenses/LICENSE
illallangi_data_education-0.3.0.dist-info/RECORD
